{
  "original_response": {
    "uids": [],
    "label": null,
    "confirmed": false,
    "manual": false,
    "width": 44.44,
    "height": 68.44,
    "yaw": -20,
    "roll": 4,
    "pitch": 7,
    "attributes": {
      "face": {
        "value": "true",
        "confidence": 89
      },
      "gender": {
        "value": "male",
        "confidence": 40
      },
      "glasses": {
        "value": "true",
        "confidence": 60
      },
      "dark_glasses": {
        "value": "true",
        "confidence": 34
      },
      "smiling": {
        "value": "false",
        "confidence": 46
      },
      "age_est": {
        "value": "44",
        "confidence": 50
      },
      "mood": {
        "value": "sad",
        "confidence": 58
      },
      "lips": {
        "value": "sealed",
        "confidence": 54
      },
      "eyes": {
        "value": "open",
        "confidence": 25
      },
      "neutral_mood": {
        "value": "false",
        "confidence": 0
      },
      "anger": {
        "value": "false",
        "confidence": 42
      },
      "disgust": {
        "value": "false",
        "confidence": 0
      },
      "fear": {
        "value": "false",
        "confidence": 0
      },
      "happiness": {
        "value": "false",
        "confidence": 0
      },
      "sadness": {
        "value": "true",
        "confidence": 58
      },
      "surprise": {
        "value": "false",
        "confidence": 0
      },
      "ethnicity": {
        "white": {
          "value": "false",
          "confidence": 24
        },
        "black": {
          "value": "false",
          "confidence": 4
        },
        "asian": {
          "value": "false",
          "confidence": 3
        },
        "indian": {
          "value": "true",
          "confidence": 66
        },
        "hispanic": {
          "value": "false",
          "confidence": 3
        }
      },
      "beard": {
        "value": "true",
        "confidence": 57
      },
      "mustache": {
        "value": "true",
        "confidence": 16
      },
      "hat": {
        "value": "false",
        "confidence": 12
      },
      "liveness": {
        "value": "true",
        "confidence": 77
      }
    },
    "points": null,
    "similarities": null,
    "tid": "TEMP_F@0e19027a075a58562d5551350086006b_ac38391966f34_59.56_47.56_0_1",
    "recognizable": true,
    "center": {
      "x": 59.56,
      "y": 47.56
    },
    "eye_left": {
      "x": 74.67,
      "y": 37.33,
      "confidence": 100,
      "id": 449
    },
    "eye_right": {
      "x": 55.56,
      "y": 35.11,
      "confidence": 97,
      "id": 450
    },
    "mouth_center": {
      "x": 64.44,
      "y": 60.44,
      "confidence": 94,
      "id": 615
    },
    "nose": {
      "x": 68.0,
      "y": 47.56,
      "confidence": 98,
      "id": 403
    }
  },
  "standardized_response": {
    "items": [
      {
        "confidence": 89.0,
        "landmarks": {
          "left_eye": [
            74.67,
            37.33
          ],
          "left_eye_top": [],
          "left_eye_right": [],
          "left_eye_bottom": [],
          "left_eye_left": [],
          "right_eye": [
            55.56,
            35.11
          ],
          "right_eye_top": [],
          "right_eye_right": [],
          "right_eye_bottom": [],
          "right_eye_left": [],
          "left_eyebrow_left": [],
          "left_eyebrow_right": [],
          "left_eyebrow_top": [],
          "right_eyebrow_left": [],
          "right_eyebrow_right": [],
          "left_pupil": [],
          "right_pupil": [],
          "nose_tip": [
            68.0,
            47.56
          ],
          "nose_bottom_right": [],
          "nose_bottom_left": [],
          "mouth_left": [],
          "mouth_right": [],
          "right_eyebrow_top": [],
          "midpoint_between_eyes": [],
          "nose_bottom_center": [],
          "nose_left_alar_out_tip": [],
          "nose_left_alar_top": [],
          "nose_right_alar_out_tip": [],
          "nose_right_alar_top": [],
          "nose_root_left": [],
          "nose_root_right": [],
          "upper_lip": [],
          "under_lip": [],
          "under_lip_bottom": [],
          "under_lip_top": [],
          "upper_lip_bottom": [],
          "upper_lip_top": [],
          "mouth_center": [
            64.44,
            60.44
          ],
          "mouth_top": [],
          "mouth_bottom": [],
          "left_ear_tragion": [],
          "right_ear_tragion": [],
          "forehead_glabella": [],
          "chin_gnathion": [],
          "chin_left_gonion": [],
          "chin_right_gonion": [],
          "upper_jawline_left": [],
          "mid_jawline_left": [],
          "mid_jawline_right": [],
          "upper_jawline_right": [],
          "left_cheek_center": [],
          "right_cheek_center": []
        },
        "emotions": {
          "joy": 0,
          "sorrow": 58,
          "anger": 42,
          "surprise": 0,
          "disgust": 0,
          "fear": 0,
          "confusion": null,
          "calm": null,
          "unknown": null,
          "neutral": 0,
          "contempt": null
        },
        "poses": {
          "pitch": null,
          "roll": null,
          "yaw": null
        },
        "age": 44.0,
        "gender": "male",
        "bounding_box": {
          "x_min": null,
          "x_max": null,
          "y_min": null,
          "y_max": null
        },
        "hair": {
          "hair_color": [],
          "bald": null,
          "invisible": null
        },
        "facial_hair": {
          "moustache": 1.0,
          "beard": 1.0,
          "sideburns": null
        },
        "quality": {
          "noise": null,
          "exposure": null,
          "blur": null,
          "brightness": null,
          "sharpness": null
        },
        "makeup": {
          "eye_make": null,
          "lip_make": null
        },
        "accessories": {
          "sunglasses": 1.0,
          "reading_glasses": null,
          "swimming_goggles": null,
          "face_mask": null,
          "eyeglasses": 1.0,
          "headwear": 0.0
        },
        "occlusions": {
          "eye_occluded": null,
          "forehead_occluded": null,
          "mouth_occluded": null
        },
        "features": {
          "eyes_open": 1.0,
          "smile": 0.0,
          "mouth_open": 0.0
        }
      }
    ]
  }
}