{
  "original_response": {
    "bboxes": [
      [
        299.0,
        123.0,
        541.0,
        398.0
      ],
      [
        549.0,
        159.0,
        1234.0,
        418.0
      ]
    ]
  },
  "standardized_response": {
    "items": [
      {
        "bounding_poly": {
          "vertices": [
            {
              "x": 299.0,
              "y": 123.0
            },
            {
              "x": 541.0,
              "y": 123.0
            },
            {
              "x": 541.0,
              "y": 398.0
            },
            {
              "x": 299.0,
              "y": 398.0
            }
          ]
        },
        "description": null,
        "score": null
      },
      {
        "bounding_poly": {
          "vertices": [
            {
              "x": 549.0,
              "y": 159.0
            },
            {
              "x": 1234.0,
              "y": 159.0
            },
            {
              "x": 1234.0,
              "y": 418.0
            },
            {
              "x": 549.0,
              "y": 418.0
            }
          ]
        },
        "description": null,
        "score": null
      }
    ]
  }
}