{
  "original_response": [
    {
      "CustomerAddress": {
        "value_type": "address",
        "value": {
          "house_number": "201",
          "po_box": null,
          "road": "Stan Fey Dr",
          "city": "Upper Marlboro",
          "state": "MD",
          "postal_code": "20774",
          "country_region": null,
          "street_address": "201 Stan Fey Dr",
          "unit": null,
          "city_district": null,
          "state_district": null,
          "suburb": null,
          "house": null,
          "level": null
        },
        "content": "201 Stan Fey Dr\nUpper Marlboro , MD 20774",
        "bounding_regions": [
          {
            "page_number": 1,
            "polygon": [
              {
                "x": 62.0,
                "y": 218.0
              },
              {
                "x": 204.0,
                "y": 218.0
              },
              {
                "x": 204.0,
                "y": 246.0
              },
              {
                "x": 62.0,
                "y": 246.0
              }
            ]
          }
        ],
        "spans": [
          {
            "offset": 256,
            "length": 41
          }
        ],
        "confidence": 0.713
      },
      "document_index": 1,
      "document_type": "invoice",
      "CustomerAddressRecipient": {
        "value_type": "string",
        "value": "Damita J Goldsmith",
        "content": "Damita J Goldsmith",
        "bounding_regions": [
          {
            "page_number": 1,
            "polygon": [
              {
                "x": 62.0,
                "y": 204.0
              },
              {
                "x": 161.0,
                "y": 204.0
              },
              {
                "x": 161.0,
                "y": 217.0
              },
              {
                "x": 62.0,
                "y": 217.0
              }
            ]
          }
        ],
        "spans": [
          {
            "offset": 237,
            "length": 18
          }
        ],
        "confidence": 0.81
      },
      "CustomerName": {
        "value_type": "string",
        "value": "Damita J Goldsmith",
        "content": "Damita J Goldsmith",
        "bounding_regions": [
          {
            "page_number": 1,
            "polygon": [
              {
                "x": 62.0,
                "y": 204.0
              },
              {
                "x": 161.0,
                "y": 204.0
              },
              {
                "x": 161.0,
                "y": 217.0
              },
              {
                "x": 62.0,
                "y": 217.0
              }
            ]
          }
        ],
        "spans": [
          {
            "offset": 237,
            "length": 18
          }
        ],
        "confidence": 0.81
      },
      "InvoiceDate": {
        "value_type": "date",
        "value": "2003-01-20",
        "content": "January 20, 2003",
        "bounding_regions": [
          {
            "page_number": 1,
            "polygon": [
              {
                "x": 561.0,
                "y": 121.0
              },
              {
                "x": 648.0,
                "y": 121.0
              },
              {
                "x": 648.0,
                "y": 134.0
              },
              {
                "x": 561.0,
                "y": 134.0
              }
            ]
          }
        ],
        "spans": [
          {
            "offset": 202,
            "length": 16
          }
        ],
        "confidence": 0.93
      },
      "InvoiceId": {
        "value_type": "string",
        "value": "014- 03",
        "content": "014- 03",
        "bounding_regions": [
          {
            "page_number": 1,
            "polygon": [
              {
                "x": 610.0,
                "y": 106.0
              },
              {
                "x": 651.0,
                "y": 108.0
              },
              {
                "x": 650.0,
                "y": 122.0
              },
              {
                "x": 609.0,
                "y": 120.0
              }
            ]
          }
        ],
        "spans": [
          {
            "offset": 154,
            "length": 7
          }
        ],
        "confidence": 0.938
      },
      "InvoiceTotal": {
        "value_type": "currency",
        "value": {
          "amount": 750.0,
          "symbol": null,
          "code": "USD"
        },
        "content": "750.00",
        "bounding_regions": [
          {
            "page_number": 1,
            "polygon": [
              {
                "x": 611.0,
                "y": 667.0
              },
              {
                "x": 645.0,
                "y": 666.0
              },
              {
                "x": 645.0,
                "y": 678.0
              },
              {
                "x": 611.0,
                "y": 678.0
              }
            ]
          }
        ],
        "spans": [
          {
            "offset": 680,
            "length": 6
          }
        ],
        "confidence": 0.79
      },
      "items": [
        {
          "value_type": "dictionary",
          "value": {
            "Amount": {
              "value_type": "currency",
              "value": {
                "amount": 750.0,
                "symbol": null,
                "code": "USD"
              },
              "content": "750 .. 00",
              "bounding_regions": [
                {
                  "page_number": 1,
                  "polygon": [
                    {
                      "x": 611.0,
                      "y": 393.0
                    },
                    {
                      "x": 649.0,
                      "y": 393.0
                    },
                    {
                      "x": 649.0,
                      "y": 405.0
                    },
                    {
                      "x": 611.0,
                      "y": 405.0
                    }
                  ]
                }
              ],
              "spans": [
                {
                  "offset": 551,
                  "length": 9
                }
              ],
              "confidence": 0.766
            },
            "Description": {
              "value_type": "string",
              "value": "Field inspection of construction on 1/19/2003 deficiencies in house\nconstruction, Garage drive way & legal support to Attorney to\n1/19/2003",
              "content": "Field inspection of construction on 1/19/2003 deficiencies in house\nconstruction, Garage drive way & legal support to Attorney to\n1/19/2003",
              "bounding_regions": [
                {
                  "page_number": 1,
                  "polygon": [
                    {
                      "x": 125.0,
                      "y": 392.0
                    },
                    {
                      "x": 463.0,
                      "y": 392.0
                    },
                    {
                      "x": 463.0,
                      "y": 459.0
                    },
                    {
                      "x": 125.0,
                      "y": 459.0
                    }
                  ]
                }
              ],
              "spans": [
                {
                  "offset": 476,
                  "length": 67
                },
                {
                  "offset": 561,
                  "length": 71
                }
              ],
              "confidence": 0.715
            },
            "Quantity": {
              "value_type": "float",
              "value": 1.0,
              "content": "1",
              "bounding_regions": [
                {
                  "page_number": 1,
                  "polygon": [
                    {
                      "x": 79.0,
                      "y": 392.0
                    },
                    {
                      "x": 82.0,
                      "y": 392.0
                    },
                    {
                      "x": 83.0,
                      "y": 403.0
                    },
                    {
                      "x": 79.0,
                      "y": 403.0
                    }
                  ]
                }
              ],
              "spans": [
                {
                  "offset": 474,
                  "length": 1
                }
              ],
              "confidence": 0.713
            },
            "UnitPrice": {
              "value_type": "currency",
              "value": {
                "amount": 750.0,
                "symbol": null,
                "code": "USD"
              },
              "content": "750.00",
              "bounding_regions": [
                {
                  "page_number": 1,
                  "polygon": [
                    {
                      "x": 530.0,
                      "y": 393.0
                    },
                    {
                      "x": 564.0,
                      "y": 393.0
                    },
                    {
                      "x": 564.0,
                      "y": 405.0
                    },
                    {
                      "x": 530.0,
                      "y": 404.0
                    }
                  ]
                }
              ],
              "spans": [
                {
                  "offset": 544,
                  "length": 6
                }
              ],
              "confidence": 0.944
            }
          },
          "content": "1\n1\nField inspection of construction on 1/19/2003 deficiencies in house\n750.00\n750 .. 00\nconstruction, Garage drive way & legal support to Attorney to\n1/19/2003",
          "bounding_regions": [
            {
              "page_number": 1,
              "polygon": [
                {
                  "x": 76.0,
                  "y": 392.0
                },
                {
                  "x": 649.0,
                  "y": 392.0
                },
                {
                  "x": 649.0,
                  "y": 459.0
                },
                {
                  "x": 76.0,
                  "y": 459.0
                }
              ]
            }
          ],
          "spans": [
            {
              "offset": 472,
              "length": 160
            }
          ],
          "confidence": 0.781
        }
      ],
      "PaymentTerm": {
        "value_type": "string",
        "value": "on receipt of service",
        "content": "on receipt of service",
        "bounding_regions": [
          {
            "page_number": 1,
            "polygon": [
              {
                "x": 562.0,
                "y": 335.0
              },
              {
                "x": 644.0,
                "y": 335.0
              },
              {
                "x": 644.0,
                "y": 347.0
              },
              {
                "x": 562.0,
                "y": 347.0
              }
            ]
          }
        ],
        "spans": [
          {
            "offset": 411,
            "length": 21
          }
        ],
        "confidence": 0.653
      },
      "RemittanceAddressRecipient": {
        "value_type": "string",
        "value": "SNG Engineering, Inc.",
        "content": "SNG Engineering, Inc.",
        "bounding_regions": [
          {
            "page_number": 1,
            "polygon": [
              {
                "x": 178.0,
                "y": 699.0
              },
              {
                "x": 291.0,
                "y": 699.0
              },
              {
                "x": 291.0,
                "y": 713.0
              },
              {
                "x": 178.0,
                "y": 713.0
              }
            ]
          }
        ],
        "spans": [
          {
            "offset": 714,
            "length": 21
          }
        ],
        "confidence": 0.886
      },
      "ServiceEndDate": {
        "value_type": "date",
        "value": "2003-01-19",
        "content": "1/19/2003",
        "bounding_regions": [
          {
            "page_number": 1,
            "polygon": [
              {
                "x": 127.0,
                "y": 446.0
              },
              {
                "x": 177.0,
                "y": 447.0
              },
              {
                "x": 178.0,
                "y": 459.0
              },
              {
                "x": 127.0,
                "y": 459.0
              }
            ]
          }
        ],
        "spans": [
          {
            "offset": 623,
            "length": 9
          }
        ],
        "confidence": 0.433
      },
      "ShippingAddress": {
        "value_type": "address",
        "value": {
          "house_number": "201",
          "po_box": null,
          "road": "Stan Fey Drive",
          "city": "Upper Marlboro",
          "state": null,
          "postal_code": null,
          "country_region": null,
          "street_address": "201 Stan Fey Drive",
          "unit": null,
          "city_district": null,
          "state_district": null,
          "suburb": null,
          "house": null,
          "level": null
        },
        "content": "201 Stan Fey Drive\nUpper Marlboro",
        "bounding_regions": [
          {
            "page_number": 1,
            "polygon": [
              {
                "x": 406.0,
                "y": 218.0
              },
              {
                "x": 503.0,
                "y": 218.0
              },
              {
                "x": 503.0,
                "y": 245.0
              },
              {
                "x": 406.0,
                "y": 245.0
              }
            ]
          }
        ],
        "spans": [
          {
            "offset": 309,
            "length": 33
          }
        ],
        "confidence": 0.509
      },
      "ShippingAddressRecipient": {
        "value_type": "string",
        "value": "Same",
        "content": "Same",
        "bounding_regions": [
          {
            "page_number": 1,
            "polygon": [
              {
                "x": 412.0,
                "y": 190.0
              },
              {
                "x": 443.0,
                "y": 190.0
              },
              {
                "x": 443.0,
                "y": 203.0
              },
              {
                "x": 412.0,
                "y": 203.0
              }
            ]
          }
        ],
        "spans": [
          {
            "offset": 232,
            "length": 4
          }
        ],
        "confidence": 0.44
      },
      "SubTotal": {
        "value_type": "currency",
        "value": {
          "amount": 750.0,
          "symbol": null,
          "code": "USD"
        },
        "content": "750.00",
        "bounding_regions": [
          {
            "page_number": 1,
            "polygon": [
              {
                "x": 611.0,
                "y": 584.0
              },
              {
                "x": 646.0,
                "y": 584.0
              },
              {
                "x": 645.0,
                "y": 596.0
              },
              {
                "x": 611.0,
                "y": 596.0
              }
            ]
          }
        ],
        "spans": [
          {
            "offset": 642,
            "length": 6
          }
        ],
        "confidence": 0.942
      },
      "VendorAddress": {
        "value_type": "address",
        "value": {
          "house_number": "344",
          "po_box": null,
          "road": "Main Street",
          "city": "Gaithersburg",
          "state": "MD",
          "postal_code": "20878",
          "country_region": null,
          "street_address": "344 Main Street Suite 200",
          "unit": "Suite 200",
          "city_district": null,
          "state_district": null,
          "suburb": null,
          "house": null,
          "level": null
        },
        "content": "344 Main Street Suite 200\nGaithersburg, MD 20878",
        "bounding_regions": [
          {
            "page_number": 1,
            "polygon": [
              {
                "x": 187.0,
                "y": 77.0
              },
              {
                "x": 323.0,
                "y": 77.0
              },
              {
                "x": 323.0,
                "y": 105.0
              },
              {
                "x": 187.0,
                "y": 105.0
              }
            ]
          }
        ],
        "spans": [
          {
            "offset": 55,
            "length": 48
          }
        ],
        "confidence": 0.886
      },
      "VendorAddressRecipient": {
        "value_type": "string",
        "value": "Consulting Engineers",
        "content": "Consulting Engineers",
        "bounding_regions": [
          {
            "page_number": 1,
            "polygon": [
              {
                "x": 188.0,
                "y": 64.0
              },
              {
                "x": 307.0,
                "y": 66.0
              },
              {
                "x": 307.0,
                "y": 81.0
              },
              {
                "x": 188.0,
                "y": 79.0
              }
            ]
          }
        ],
        "spans": [
          {
            "offset": 34,
            "length": 20
          }
        ],
        "confidence": 0.503
      },
      "VendorName": {
        "value_type": "string",
        "value": "SNG Engineering, Inc.\nSNG",
        "content": "SNG Engineering, Inc.\nSNG",
        "bounding_regions": [
          {
            "page_number": 1,
            "polygon": [
              {
                "x": 49.0,
                "y": 40.0
              },
              {
                "x": 405.0,
                "y": 42.0
              },
              {
                "x": 405.0,
                "y": 122.0
              },
              {
                "x": 49.0,
                "y": 121.0
              }
            ]
          }
        ],
        "spans": [
          {
            "offset": 0,
            "length": 25
          }
        ],
        "confidence": 0.308
      }
    }
  ],
  "standardized_response": {
    "extracted_data": [
      {
        "customer_information": {
          "name": "Damita J Goldsmith",
          "id_reference": null,
          "mailling_address": "201 Stan Fey Dr\nUpper Marlboro , MD 20774",
          "billing_address": null,
          "shipping_address": "201 Stan Fey Drive\nUpper Marlboro",
          "service_address": null,
          "remittance_address": null,
          "email": null,
          "phone": null,
          "vat_number": null,
          "abn_number": null,
          "gst_number": null,
          "pan_number": null,
          "business_number": null,
          "siret_number": null,
          "siren_number": null,
          "customer_number": null,
          "coc_number": null,
          "fiscal_number": null,
          "registration_number": null,
          "tax_id": null,
          "website": null,
          "remit_to_name": "Damita J Goldsmith",
          "city": null,
          "country": null,
          "house_number": null,
          "province": null,
          "street_name": null,
          "zip_code": null,
          "municipality": null
        },
        "merchant_information": {
          "name": "SNG Engineering, Inc.\nSNG",
          "address": "344 Main Street Suite 200\nGaithersburg, MD 20878",
          "phone": null,
          "tax_id": null,
          "id_reference": null,
          "vat_number": null,
          "abn_number": null,
          "gst_number": null,
          "business_number": null,
          "siret_number": null,
          "siren_number": null,
          "pan_number": null,
          "coc_number": null,
          "fiscal_number": null,
          "email": null,
          "fax": null,
          "website": null,
          "registration": null,
          "city": null,
          "country": null,
          "house_number": null,
          "province": null,
          "street_name": null,
          "zip_code": null,
          "country_code": null
        },
        "payment_information": {
          "amount_due": null,
          "amount_tip": null,
          "amount_shipping": null,
          "amount_change": null,
          "amount_paid": null,
          "invoice_total": 750.0,
          "subtotal": 750.0,
          "total_tax": null,
          "tax_rate": null,
          "discount": null,
          "gratuity": null,
          "service_charge": null,
          "previous_unpaid_balance": null,
          "prior_balance": null,
          "payment_terms": "on receipt of service",
          "payment_method": null,
          "payment_card_number": null,
          "payment_auth_code": null,
          "shipping_handling_charge": null,
          "transaction_number": null,
          "transaction_reference": null
        },
        "financial_document_information": {
          "invoice_id": "014- 03",
          "purchase_order": null,
          "invoice_date": "2003-01-20",
          "time": null,
          "invoice_due_date": null,
          "service_start_date": null,
          "service_end_date": null,
          "reference": null,
          "biller_code": null,
          "order_date": null,
          "tracking_number": null,
          "barcodes": []
        },
        "local": {
          "currency": null,
          "currency_code": "USD",
          "currency_exchange_rate": null,
          "country": null,
          "language": null
        },
        "bank": {
          "iban": null,
          "swift": null,
          "bsb": null,
          "sort_code": null,
          "account_number": null,
          "routing_number": null,
          "bic": null
        },
        "item_lines": [
          {
            "tax": null,
            "amount_line": 750.0,
            "description": "Field inspection of construction on 1/19/2003 deficiencies in house\nconstruction, Garage drive way & legal support to Attorney to\n1/19/2003",
            "quantity": 1.0,
            "unit_price": 750.0,
            "unit_type": null,
            "date": null,
            "product_code": null,
            "purchase_order": null,
            "tax_rate": null,
            "base_total": null,
            "sub_total": null,
            "discount_amount": null,
            "discount_rate": null,
            "discount_code": null,
            "order_number": null,
            "title": null
          }
        ],
        "invoice_metadata": {
          "document_index": 1,
          "document_page_number": 1,
          "document_type": "invoice"
        }
      }
    ]
  }
}